odoo/addons/fleet_vehicle_history_date_end/README.rst
odoo/addons/fleet_vehicle_history_date_end/__init__.py
odoo/addons/fleet_vehicle_history_date_end/__manifest__.py
odoo/addons/fleet_vehicle_history_date_end/i18n/es.po
odoo/addons/fleet_vehicle_history_date_end/i18n/fleet_vehicle_history_date_end.pot
odoo/addons/fleet_vehicle_history_date_end/i18n/it.po
odoo/addons/fleet_vehicle_history_date_end/i18n/pt_BR.po
odoo/addons/fleet_vehicle_history_date_end/models/__init__.py
odoo/addons/fleet_vehicle_history_date_end/models/fleet_vehicle_assignation_log.py
odoo/addons/fleet_vehicle_history_date_end/readme/CONTRIBUTORS.rst
odoo/addons/fleet_vehicle_history_date_end/readme/DESCRIPTION.rst
odoo/addons/fleet_vehicle_history_date_end/static/description/icon.png
odoo/addons/fleet_vehicle_history_date_end/static/description/index.html
odoo/addons/fleet_vehicle_history_date_end/tests/__init__.py
odoo/addons/fleet_vehicle_history_date_end/tests/test_vehicle_history_date_end.py
odoo14_addon_fleet_vehicle_history_date_end-14.0.1.0.1.dev11.dist-info/METADATA
odoo14_addon_fleet_vehicle_history_date_end-14.0.1.0.1.dev11.dist-info/WHEEL
odoo14_addon_fleet_vehicle_history_date_end-14.0.1.0.1.dev11.dist-info/top_level.txt
odoo14_addon_fleet_vehicle_history_date_end-14.0.1.0.1.dev11.dist-info/RECORD
